malnet_db-0.1.0-py3.7-nspkg.pth
malnet/db/__init__.py
malnet/db/fs.py
malnet/db/model.py
malnet/db/test.py
malnet/db/utils.py
malnet_db-0.1.0.dist-info/LICENSE
malnet_db-0.1.0.dist-info/METADATA
malnet_db-0.1.0.dist-info/WHEEL
malnet_db-0.1.0.dist-info/namespace_packages.txt
malnet_db-0.1.0.dist-info/top_level.txt
malnet_db-0.1.0.dist-info/zip-safe
malnet_db-0.1.0.dist-info/RECORD
